ugapi/TabSpider.py
ugapi/WikiSpider.py
ugapi/__init__.py
ugapi/enums.py
ugapi-0.1.6.dist-info/LICENSE.txt
ugapi-0.1.6.dist-info/METADATA
ugapi-0.1.6.dist-info/WHEEL
ugapi-0.1.6.dist-info/top_level.txt
ugapi-0.1.6.dist-info/RECORD
