Metadata-Version: 2.1
Name: ugapi
Version: 0.1.6
Summary: Ultimate-Guitar Tab API
Home-page: http://github.com/doodoroma/ugapi
Author: Adam Meszaros
Author-email: doodoroma@gmail.com
License: MIT
Platform: UNKNOWN
Requires-Dist: scrapy
Requires-Dist: pandas
